Workbook

Sheet Diagrama ER (corregido)

Sheet Invetario de Tablas
A1: Modelo Físico - Tablas resultantes del Diccionario de Datos MEJORADO
A2: INVENTARIO DE TABLAS
A3: # | B3: Tabla | C3: Descripción Tabla | D3: Observaciones
A4: 1 | B4: rol | C4: Almacena los roles de los usuarios | D4: Tabla independiente
A5: =A4+1 -> 2 | B5: tipo_usuario | C5: Clasifica los tipos de usuarios | D5: Tabla independiente
A6: =A5+1 -> 3 | B6: usuario | C6: Guarda la información principal de los usuarios | D6: Relacionada con rol y tipo_usuario
A7: =A6+1 -> 4 | B7: perfil | C7: Contiene información extendida del usuario | D7: Usa JSONB
A8: =A7+1 -> 5 | B8: publicacion | C8: Registra publicaciones de usuarios | D8: Depende de usuario
A9: =A8+1 -> 6 | B9: comentario | C9: Guarda comentarios de publicaciones | D9: Relación usuario-publicación
A10: =A9+1 -> 7 | B10: grupo_social | C10: Almacena grupos académicos o sociales | D10: Depende de usuario
A11: =A10+1 -> 8 | B11: evento | C11: Registra eventos estudiantiles | D11: Depende de usuario
A12: =A11+1 -> 9 | B12: servicio | C12: Registra servicios publicados | D12: Depende de usuario
A13: =A12+1 -> 10 | B13: producto | C13: Registra productos publicados | D13: Depende de usuario
A14: =A13+1 -> 11 | B14: grupo_usuarios | C14: Relaciona usuarios con grupos | D14: Tabla puente
A15: =A14+1 -> 12 | B15: usuario_habilidad | C15: Relaciona usuarios con habilidades | D15: Tabla puente
A16: =A15+1 -> 13
A17: =A16+1 -> 14
A18: =A17+1 -> 15
A19: =A18+1 -> 16
A20: =A19+1 -> 17
A21: =A20+1 -> 18
A22: =A21+1 -> 19
A23: =A22+1 -> 20
A24: =A23+1 -> 21
A25: =A24+1 -> 22
A26: =A25+1 -> 23
A27: =A26+1 -> 24
A28: =A27+1 -> 25

Sheet Diccionario Datos - PostgreSQL
A1: PostgreSQL - Tablas en Detalle
A3: ='Invetario de Tablas'!A4 -> 1 | B3: Tabla | C3: ='Invetario de Tablas'!B4 -> rol | G3: Descripción Tabla | K3: ='Invetario de Tablas'!C4 -> Almacena los roles de los usuarios | X3: Versión
A4: # | B4: Campo | C4: Descripción Campo | G4: Tipo Dato - PostgreSQL | K4: Tamaño | O4: Nulo | R4: PK | T4: FK | V4: UK | X4: Nota/Comentarios
A5: 1 | B5: id_rol | C5: Identificador único del rol | G5: SERIAL | O5: No | R5: S | X5: Clave primaria autoincremental
A6: 2 | B6: nombre | C6: Nombre del rol del usuario | G6: VARCHAR | K6: 50 | O6: No | V6: S | X6: Debe ser único
A7: 3 | B7: descripcion | C7: Descripción del rol | G7: TEXT | O7: Sí | X7: Información adicional del rol
A8: 4 | B8: estado | C8: Estado del rol | G8: BOOLEAN | O8: No | X8: TRUE activo / FALSE inactivo
A9: 5 | B9: fecha_creacion | C9: Fecha de creación del rol | G9: TIMESTAMP | O9: No | X9: Registro automático
A11: N
A12: NOTA: En las columnas PK, FK y UK debe colocar “S” solamente cuando aplique. En la columna “Nulo” coloque “No” en caso de que el campo debe estar valorizado
A14: ='Invetario de Tablas'!A5 -> 2 | B14: Tabla | C14: ='Invetario de Tablas'!B5 -> tipo_usuario | G14: Descripción Tabla | K14: ='Invetario de Tablas'!C5 -> Clasifica los tipos de usuarios | X14: Versión | Y14: 1
A15: # | B15: Campo | C15: Descripción Campo | G15: Tipo Dato - PostgreSQL | K15: Tamaño | O15: Nulo | R15: PK | T15: FK | V15: UK | X15: Nota/Comentarios
A16: 1 | B16: id_tipo_usuario | C16: Identificador del tipo de usuario | G16: SERIAL | O16: No | R16: S | X16: Clave primaria
A17: 2 | B17: nombre_tipo | C17: Nombre del tipo de usuario | G17: VARCHAR | K17: 50 | O17: No | V17: S | X17: Debe ser único
A18: 3 | B18: descripcion | C18: Descripción del tipo de usuario | G18: TEXT | O18: Sí | X18: Información adicional
A19: 4 | B19: nivel_acceso | C19: Nivel de permisos del usuario | G19: INTEGER | O19: No | X19: Control de acceso
A20: 5 | B20: fecha_creacion | C20: Fecha de creación | G20: TIMESTAMP | O20: No | X20: Registro automático
A22: N
A24: Puede seguir agregando tablas. Solamente tiene que copiar y pegar hacia abajo hasta que complete todas las tablas OJO - ATENCIÓN - RECUERDE COLOCAR LAS REFERENCIAS DE LAS TABLAS: NÚMERO , NOMBRE, DESCRIPCIóN
A26: 3 | B26: Tabla | C26: USUARIO | G26: Descripción Tabla | K26: Guarda la información principal de los usuarios | X26: Versión | Y26: 1
A27: # | B27: Campo | C27: Descripción Campo | G27: Tipo Dato - PostgreSQL | K27: Tamaño | O27: Nulo | R27: PK | T27: FK | V27: UK | X27: Nota/Comentarios
A28: 1 | B28: id_tipo_usuario | C28: Identificador único del usuario | G28: SERIAL | O28: No | R28: S | X28: Clave primaria
A29: 2 | B29: nombre | C29: Nombre completo del usuario | G29: VARCHAR | K29: 150 | O29: No | X29: Nombre del estudiante
A30: 3 | B30: correo | C30: Correo institucional o personal | G30: VARCHAR | K30: 100 | O30: No | V30: S | X30: Debe ser único
A31: 4 | B31: contrasena | C31: Contraseña cifrada del usuario | G31: VARCHAR | K31: 255 | O31: No | X31: Seguridad del sistema
A32: 5 | B32: fecha_registro | C32: Fecha de registro del usuario | G32: TIMESTAMP | O32: No | X32: Registro automático
B33: id_rol | C33: Rol asignado al usuario | G33: INTEGER | O33: No | T33: S | X33: Relación con tabla rol
B34: id_tipo_usuario | C34: Tipo de usuario | G34: INTEGER | O34: No | T34: S | X34: Relación con tipo_usuario
B35: estado | C35: Estado de la cuenta | G35: BOOLEAN | O35: No | X35: TRUE activo / FALSE inactivo
A36: N
A39: 4 | B39: Tabla | C39: PERFIL | G39: Descripción Tabla | K39: Contiene información extendida del usuario | X39: Versión | Y39: 1.0
A40: # | B40: Campo | C40: Descripción Campo | G40: Tipo Dato - PostgreSQL | K40: Tamaño | O40: Nulo | R40: PK | T40: FK | V40: UK | X40: Nota/Comentarios
A41: 1 | B41: id_perfil | C41: Identificador del perfil | G41: SERIAL | O41: No | R41: S | X41: Clave primaria
A42: 2 | B42: id_usuario | C42: Usuario propietario del perfil | G42: INTEGER | O42: No | T42: S | X42: Relación con usuario
A43: 3 | B43: biografia | C43: Información personal del usuario | G43: TEXT | O43: Sí | X43: Descripción del perfil
A44: 4 | B44: intereses | C44: Intereses académicos o sociales | G44: JSONB | O44: Sí | X44: Manejo de Big Data
A45: 5 | B45: habilidades | C45: Habilidades técnicas o deportivas | G45: JSONB | O45: Sí | X45: Información semiestructurada
A46: 6 | B46: foto_perfil | C46: URL de imagen del perfil | G46: VARCHAR | K46: 255 | O46: Sí | X46: Ruta de imagen
A47: 7 | B47: fecha_actualizacion | C47: Fecha de actualización | G47: TIMESTAMP | O47: No | X47: Control de cambios
A48: N
A51: 5 | B51: Tabla | C51: PUBLICACION | G51: Descripción Tabla | K51: Registra publicaciones de usuarios | X51: Versión | Y51: 1
A52: # | B52: Campo | C52: Descripción Campo | G52: Tipo Dato - PostgreSQL | K52: Tamaño | O52: Nulo | R52: PK | T52: FK | V52: UK | X52: Nota/Comentarios
A53: 1 | B53: id_publicacion | C53: Identificador de publicación | G53: SERIAL | O53: No | R53: S | X53: Clave primaria
A54: 2 | B54: id_usuario | C54: Usuario que publica | G54: INTEGER | O54: No | T54: S | X54: Relación con usuario
A55: 3 | B55: contenido | C55: Texto de la publicación | G55: TEXT | O55: No | X55: Contenido principal
A56: 4 | B56: multimedia | C56: Recursos multimedia | G56: JSONB | O56: SI | X56: Imágenes o videos
A57: 5 | B57: fecha_publicacion | C57: Fecha de publicación | G57: TIMESTAMP | O57: No | X57: Registro automático
A58: 6 | B58: privacidad | C58: Nivel de privacidad | G58: VARCHAR | K58: 20 | O58: No | X58: Pública o privada
A59: N
A62: 6 | B62: Tabla | C62: COMENTARIO | G62: Descripción Tabla | K62: Guarda comentarios de publicaciones | X62: Versión | Y62: 1
A63: # | B63: Campo | C63: Descripción Campo | G63: Tipo Dato - PostgreSQL | K63: Tamaño | O63: Nulo | R63: PK | T63: FK | V63: UK | X63: Nota/Comentarios
A64: 1 | B64: id_comentario | C64: Identificador del comentario | G64: SERIAL | O64: No | R64: S | X64: Clave primaria
A65: 2 | B65: id_publicacion | C65: Publicación relacionada | G65: VARCHAR | K65: 50 | O65: No | V65: S | X65: Debe ser único
A66: 3 | B66: id_usuario | C66: Descripción del tipo de usuario | G66: TEXT | O66: Sí | X66: Información adicional
A67: 4 | B67: contenido | C67: Nivel de permisos del usuario | G67: INTEGER | O67: No | X67: Control de acceso
A68: 5 | B68: fecha_comentario | C68: Fecha de creación | G68: TIMESTAMP | O68: No | X68: Registro automático
A70: N
A73: 7 | B73: Tabla | C73: grupo_social | G73: Descripción Tabla | K73: Almacena grupos académicos o sociales | X73: Versión | Y73: 1
A74: # | B74: Campo | C74: Descripción Campo | G74: Tipo Dato - PostgreSQL | K74: Tamaño | O74: Nulo | R74: PK | T74: FK | V74: UK | X74: Nota/Comentarios
A75: 1 | B75: id_grupo | C75: Identificador del grupo | G75: SERIAL | O75: No | R75: S | X75: Clave primaria
A76: 2 | B76: nombre_grupo | C76: Nombre del grupo | G76: VARCHAR | K76: 100 | O76: No | X76: Nombre visible
A77: 3 | B77: descripcion | C77: Descripción del grupo | G77: TEXT | O77: Sí | X77: Información general
A78: 4 | B78: id_usuario_creador | C78: Usuario creador del grupo | G78: INTEGER | O78: No | T78: S | X78: Relación con usuario
A79: 5 | B79: fecha_creacion | C79: Fecha de creación | G79: TIMESTAMP | O79: No | X79: Registro automático
A81: N
A84: 8 | B84: Tabla | C84: evento | G84: Descripción Tabla | K84: Registra eventos estudiantiles | X84: Versión | Y84: 1
A85: # | B85: Campo | C85: Descripción Campo | G85: Tipo Dato - PostgreSQL | K85: Tamaño | O85: Nulo | R85: PK | T85: FK | V85: UK | X85: Nota/Comentarios
A86: 1 | B86: id_evento | C86: Identificador del evento | G86: SERIAL | O86: No | R86: S | X86: Clave primaria
A87: 2 | B87: titulo | C87: Nombre del evento | G87: VARCHAR | K87: 150 | O87: No | X87: Título del evento
A88: 3 | B88: descripcion | C88: Descripción del evento | G88: TEXT | O88: Sí | X88: Información detallada
A89: 4 | B89: fecha_evento | C89: Fecha del evento | G89: DATE | O89: No | X89: Fecha programada
A90: 5 | B90: ubicacion | C90: Lugar del evento | G90: VARCHAR | K90: 150 | O90: Sí | X90: Lugar físico o virtual
A91: 6 | B91: id_usuario | C91: Usuario organizador | G91: INTEGER | O91: No | T91: S | X91: Relación con usuario
A92: N
A95: 9 | B95: Tabla | C95: servicio | G95: Descripción Tabla | K95: Registra servicios ofrecidos | X95: Versión | Y95: 1
A96: # | B96: Campo | C96: Descripción Campo | G96: Tipo Dato - PostgreSQL | K96: Tamaño | O96: Nulo | R96: PK | T96: FK | V96: UK | X96: Nota/Comentarios
A97: 1 | B97: id_servicio | C97: Identificador del servicio | G97: SERIAL | O97: No | R97: S | X97: Clave primaria
A98: 2 | B98: titulo | C98: Nombre del servicio | G98: VARCHAR | K98: 100 | O98: No | X98: Servicio publicado
A99: 3 | B99: descripcion | C99: Descripción del servicio | G99: TEXT | O99: Sí | X99: Información detallada
A100: 4 | B100: precio | C100: Valor del servicio | G100: NUMERIC | K100: 10.2 | O100: No | X100: Precio monetario
A101: 5 | B101: id_usuario | C101: Usuario que ofrece el servicio | G101: INTEGER | O101: No | T101: S | X101: Relación con usuario
A102: 6 | B102: fecha_publicacion | C102: Fecha de publicación | G102: TIMESTAMP | O102: No | X102: Registro automático
A103: N
A106: 10 | B106: Tabla | C106: producto | G106: Descripción Tabla | K106: Registra productos publicados | X106: Versión | Y106: 1
A107: # | B107: Campo | C107: Descripción Campo | G107: Tipo Dato - PostgreSQL | K107: Tamaño | O107: Nulo | R107: PK | T107: FK | V107: UK | X107: Nota/Comentarios
A108: 1 | B108: id_producto | C108: Identificador del producto | G108: SERIAL | O108: No | R108: S | X108: Clave primaria
A109: 2 | B109: nombre_producto | C109: Nombre del producto | G109: VARCHAR | K109: 100 | O109: No | X109: Producto publicado
A110: 3 | B110: descripcion | C110: Descripción del producto | G110: TEXT | O110: Sí | X110: Información detallada
A111: 4 | B111: precio | C111: Valor del producto | G111: NUMERIC | K111: 10.2 | O111: No | X111: Precio monetario
A112: 5 | B112: stock | C112: Cantidad disponible | G112: INTEGER | O112: No | X112: Control de inventario
B113: id_usuario | C113: Usuario que publica | G113: INTEGER | O113: No | T113: S | X113: Relación con usuario
A114: N
A117: 11 | B117: Tabla | C117: grupo_usuarios | G117: Descripción Tabla | K117: Relaciona usuarios con grupos sociales | X117: Versión | Y117: 1
A118: # | B118: Campo | C118: Descripción Campo | G118: Tipo Dato - PostgreSQL | K118: Tamaño | O118: Nulo | R118: PK | T118: FK | V118: UK | X118: Nota/Comentarios
A119: 1 | B119: id_grupo_usuario | C119: Identificador de la relación | G119: SERIAL | O119: No | R119: S | X119: Clave primaria
A120: 2 | B120: id_grupo | C120: Grupo relacionado | G120: INTEGER | O120: No | T120: S | X120: Relación con grupo_social
A121: 3 | B121: id_usuario | C121: Usuario relacionado | G121: INTEGER | O121: Sí | T121: S | X121: Relación con usuario
A122: 4 | B122: fecha_union | C122: Fecha de ingreso al grupo | G122: TIMESTAMP | O122: No | X122: Registro automático
A123: 5 | B123: rol_grupo | C123: Rol del usuario dentro del grupo | G123: VARCHAR | K123: 50 | O123: Sí | X123: Administrador o miembro
A125: N
...
